AUTHORS.txt
CHANGES.txt
LICENSE.txt
MANIFEST.in
README.rst
setup.cfg
setup.py
appfy/__init__.py
appfy.recipe.gae.egg-info/PKG-INFO
appfy.recipe.gae.egg-info/SOURCES.txt
appfy.recipe.gae.egg-info/dependency_links.txt
appfy.recipe.gae.egg-info/entry_points.txt
appfy.recipe.gae.egg-info/not-zip-safe
appfy.recipe.gae.egg-info/requires.txt
appfy.recipe.gae.egg-info/top_level.txt
appfy/recipe/__init__.py
appfy/recipe/download.py
appfy/recipe/utils.py
appfy/recipe/gae/__init__.py
appfy/recipe/gae/app_lib.py
appfy/recipe/gae/sdk.py
appfy/recipe/gae/tools.py
appfy/recipe/gae/scripts/__init__.py
appfy/recipe/gae/tests/test_utils.py