Metadata-Version: 1.1
Name: appfy.recipe.gae
Version: 0.9.10
Summary: Buildout recipes for App Engine development.
Home-page: https://github.com/prmtl/appfy.recipe.gae
Author: Sebastian Kalinowski
Author-email: sebastian@kalinowski.eu
License: Apache Software License
Keywords: buildout recipe google app engine appengine gae zc.buildout appfy tipfy
Platform: UNKNOWN
Classifier: Development Status :: 4 - Beta
Classifier: Framework :: Buildout
Classifier: Intended Audience :: Developers
Classifier: License :: OSI Approved :: Apache Software License
Classifier: Topic :: Software Development :: Build Tools
Classifier: Topic :: Software Development :: Libraries :: Python Modules
